mcp_ableton_live/__init__.py
mcp_ableton_live/server.py
mcp_ableton_live-0.1.0.dist-info/licenses/LICENSE
mcp_ableton_live-0.1.0.dist-info/METADATA
mcp_ableton_live-0.1.0.dist-info/WHEEL
mcp_ableton_live-0.1.0.dist-info/entry_points.txt
mcp_ableton_live-0.1.0.dist-info/top_level.txt
mcp_ableton_live-0.1.0.dist-info/RECORD
